gohighlevel_api_client-1.0.0b1.dist-info/licenses/LICENSE
highlevel/__init__.py
highlevel/error.py
highlevel/highlevel.py
highlevel/constants/__init__.py
highlevel/constants/user_types.py
highlevel/logging/__init__.py
highlevel/logging/log_level.py
highlevel/logging/logger.py
highlevel/services/__init__.py
highlevel/services/associations/__init__.py
highlevel/services/associations/associations.py
highlevel/services/associations/models/__init__.py
highlevel/services/associations/models/associations.py
highlevel/services/blogs/__init__.py
highlevel/services/blogs/blogs.py
highlevel/services/blogs/models/__init__.py
highlevel/services/blogs/models/blogs.py
highlevel/services/businesses/__init__.py
highlevel/services/businesses/businesses.py
highlevel/services/businesses/models/__init__.py
highlevel/services/businesses/models/businesses.py
highlevel/services/calendars/__init__.py
highlevel/services/calendars/calendars.py
highlevel/services/calendars/models/__init__.py
highlevel/services/calendars/models/calendars.py
highlevel/services/campaigns/__init__.py
highlevel/services/campaigns/campaigns.py
highlevel/services/campaigns/models/__init__.py
highlevel/services/campaigns/models/campaigns.py
highlevel/services/companies/__init__.py
highlevel/services/companies/companies.py
highlevel/services/companies/models/__init__.py
highlevel/services/companies/models/companies.py
highlevel/services/contacts/__init__.py
highlevel/services/contacts/contacts.py
highlevel/services/contacts/models/__init__.py
highlevel/services/contacts/models/contacts.py
highlevel/services/conversations/__init__.py
highlevel/services/conversations/conversations.py
highlevel/services/conversations/models/__init__.py
highlevel/services/conversations/models/conversations.py
highlevel/services/courses/__init__.py
highlevel/services/courses/courses.py
highlevel/services/courses/models/__init__.py
highlevel/services/courses/models/courses.py
highlevel/services/custom_fields/__init__.py
highlevel/services/custom_fields/custom_fields.py
gohighlevel_api_client-1.0.0b1.dist-info/METADATA
gohighlevel_api_client-1.0.0b1.dist-info/WHEEL
gohighlevel_api_client-1.0.0b1.dist-info/top_level.txt
gohighlevel_api_client-1.0.0b1.dist-info/RECORD
