Metadata-Version: 2.4
Name: gohighlevel-api-client
Version: 1.0.0b1
Summary: GoHighLevel Python SDK - Official API client for GoHighLevel platform
Author-email: HighLevel <marketplace@gohighlevel.com>
License: MIT
Project-URL: Homepage, https://github.com/GoHighLevel/highlevel-api-python
Project-URL: Documentation, https://marketplace.gohighlevel.com/docs/
Project-URL: Repository, https://github.com/GoHighLevel/highlevel-api-python
Project-URL: Bug Tracker, https://github.com/GoHighLevel/highlevel-api-python/issues
Project-URL: Changelog, https://github.com/GoHighLevel/highlevel-api-python/blob/main/CHANGELOG.md
Keywords: gohighlevel,api,sdk,client,crm,marketing,automation
Requires-Python: >=3.8
License-File: LICENSE
Requires-Dist: httpx>=0.24.0
Requires-Dist: pydantic>=2.0.0
Requires-Dist: pymongo>=4.0.0
Requires-Dist: cryptography>=3.0.0
Dynamic: license-file
